multilabel3rc/__init__.py
multilabel3rc-0.0.1.dist-info/LICENCE
multilabel3rc-0.0.1.dist-info/METADATA
multilabel3rc-0.0.1.dist-info/WHEEL
multilabel3rc-0.0.1.dist-info/top_level.txt
multilabel3rc-0.0.1.dist-info/RECORD
